evtx-0.8.9.dist-info/METADATA
evtx-0.8.9.dist-info/WHEEL
evtx/__init__.py
evtx/evtx.abi3.so
evtx-0.8.9.dist-info/RECORD
