Metadata-Version: 2.4
Name: evtx
Version: 0.8.9
Classifier: Development Status :: 3 - Alpha
Classifier: Intended Audience :: Developers
Classifier: License :: OSI Approved :: MIT License
Classifier: Operating System :: MacOS :: MacOS X
Classifier: Operating System :: POSIX
Classifier: Programming Language :: Python :: Implementation :: CPython
Classifier: Programming Language :: Python :: Implementation :: PyPy
Classifier: Programming Language :: Python
Classifier: Programming Language :: Rust
Requires-Dist: pytest ; extra == 'test'
Provides-Extra: test
Summary: Python bindings for https://github.com/omerbenamram/evtx
Author: Omer Ben-Amram <omerbenamram@gmail.com>
Author-email: Omer Ben-Amram <omerbenamram@gmail.com>
License: MIT/Apache-2.0
Requires-Python: >=3.7
